[
  {
    "title": "管理",
    "member": [
      {
        "title": "管理室",
        "url": "http://komica2.net/f10/",
        "priority": 9995
      }
    ]
  },
  {
    "title": "畫像板",
    "member": [
      {
        "title": "二次裡A",
        "url": "http://komica2.net/51/index.htm"
      },
      {
        "title": "二次裡B",
        "url": "http://komica2.net/54/index.htm"
      },
      {
        "title": "三次元裡",
        "url": "http://komica2.net/43/index.htm"
      },
      {
        "title": "動畫裡",
        "url": "http://2cat.org/~hanime/"
      },
      {
        "title": "遊戲裡",
        "url": "http://komica2.net/59/index.htm"
      },
      {
        "title": "Alicesoft",
        "url": "http://komica2.net/alicesoft/"
      },
      {
        "title": "3D裡",
        "url": "http://komica2.net/66/index.htm",
        "priority": 9995
      },
      {
        "title": "塗鴉裡",
        "url": "http://komica2.net/55/index.htm"
      },
      {
        "title": "壁紙裡",
        "url": "http://komica2.net/wallpaper/"
      },
      {
        "title": "Figure 裡",
        "url": "http://komica2.net/wallpaper/",
        "priority": 9990
      },
      {
        "title": "玩偶裡",
        "url": "http://komica2.net/doll/",
        "priority": 9990
      },
      {
        "title": "交易合購裡",
        "url": "http://komica2.net/70/"
      },
      {
        "title": "成人玩具",
        "url": "http://2cat.org/~toy/"
      },
      {
        "title": "東方裡",
        "url": "http://komica.peroneko.org/touhou/"
      },
      {
        "title": "獸裡",
        "url": "http://komica2.net/34/index.htm"
      },
      {
        "title": "機娘裡",
        "url": "http://cyber.boguspix.com/"
      },
      {
        "title": "觸手裡",
        "url": "http://p.komica.acg.club.tw/k2slime/"
      },
      {
        "title": "足襪",
        "url": "http://komica2.net/stock/"
      },
      {
        "title": "惡搞裡",
        "url": "http://komica2.net/48/index.htm"
      },
      {
        "title": "偽娘裡",
        "url": "http://2cat.org/~futa/"
      },
      {
        "title": "YURI",
        "url": "http://komica2.net/31/index.htm"
      },
      {
        "title": "YAOI",
        "url": "http://komica2.net/32/index.htm"
      },
      {
        "title": "詢問裡",
        "url": "http://majeur.zawarudo.org/demande/"
      },
      {
        "title": "知識裡",
        "url": "http://2cat.org/~know/"
      },
      {
        "title": "改造裡",
        "url": "http://komica2.net/kaizou/"
      },
      {
        "title": "成人音聲",
        "url": "http://komica2.net/hvoice/"
      },
      {
        "title": "小說裡",
        "url": "http://komica2.net/63/index.htm"
      },
      {
        "title": "高解析裡",
        "url": "http://2cat.org/~hisoura/"
      },
      {
        "title": "GIF裡",
        "url": "http://2cat.org/~gifura/"
      },
      {
        "title": "宣傳裡",
        "url": "http://komica2.net/21d/index.htm"
      }
    ]
  },
  {
    "title": "文字板",
    "member": [
      {
        "title": "雜談",
        "url": "http://komica2.net/f11/",
        "priority": 9995
      },
      {
        "title": "寫作裡",
        "url": "http://komica2.net/f12/",
        "priority": 9995
      },
      {
        "title": "寫作資料庫",
        "url": "http://komica2.net/f12_archive/",
        "priority": 9995
      }
    ]
  },
  {
    "title": "其他",
    "member": [
      {
        "title": "精華裡",
        "url": "http://komica2.net/up/",
        "priority": 9995
      }
    ]
  }
]
